kv_text_processing/__init__.py
kv_text_processing/img_to_text.py
kv_text_processing-0.1.1.dist-info/METADATA
kv_text_processing-0.1.1.dist-info/WHEEL
kv_text_processing-0.1.1.dist-info/top_level.txt
kv_text_processing-0.1.1.dist-info/RECORD
