Metadata-Version: 2.1
Name: kv-text-processing
Version: 0.1.1
Author-email: Justin Bui <jmbui@klangverso.com>
Requires-Python: >=3.8
Requires-Dist: pytesseract
Requires-Dist: opencv-python
